yay/__init__.py
yay_digitalsparky-0.0.1.dist-info/LICENSE
yay_digitalsparky-0.0.1.dist-info/METADATA
yay_digitalsparky-0.0.1.dist-info/WHEEL
yay_digitalsparky-0.0.1.dist-info/top_level.txt
yay_digitalsparky-0.0.1.dist-info/RECORD
