Metadata-Version: 2.1
Name: yay-digitalsparky
Version: 0.0.1
Summary: Simple Python interface to Arch Linux package manager (yay)
Home-page: https://github.com/digitalsparky/python-yay
Author: Matt Spurrier
Author-email: matthew@spurrier.com.au
License: GPLv3
Download-URL: https://github.com/digitalsparky/python-yay/archive/0.0.1.tar.gz
Keywords: yay,arch linux
Platform: UNKNOWN
Classifier: Development Status :: 3 - Alpha
Classifier: License :: OSI Approved :: GNU General Public License v3 or later (GPLv3+)
Classifier: Operating System :: Unix
Classifier: Topic :: System :: Software Distribution
Requires-Python: >=3.6
